complexipy/__init__.py
complexipy/_complexipy.cpython-310-darwin.so
complexipy/_complexipy.pyi
complexipy/api.py
complexipy/main.py
complexipy/py.typed
complexipy/types.py
complexipy/utils/__init__.py
complexipy/utils/cache.py
complexipy/utils/csv.py
complexipy/utils/json.py
complexipy/utils/output.py
complexipy/utils/snapshot.py
complexipy/utils/toml.py
complexipy-5.1.0.dist-info/licenses/LICENSE
complexipy-5.1.0.dist-info/METADATA
complexipy-5.1.0.dist-info/WHEEL
complexipy-5.1.0.dist-info/entry_points.txt
complexipy-5.1.0.dist-info/RECORD
