Metadata-Version: 2.4
Name: complexipy
Version: 5.1.0
Classifier: Development Status :: 5 - Production/Stable
Classifier: Environment :: Console
Classifier: Intended Audience :: Developers
Classifier: Operating System :: OS Independent
Classifier: License :: OSI Approved :: MIT License
Classifier: Programming Language :: Python
Classifier: Programming Language :: Python :: 3.8
Classifier: Programming Language :: Python :: 3.9
Classifier: Programming Language :: Python :: 3.10
Classifier: Programming Language :: Python :: 3.11
Classifier: Programming Language :: Python :: 3.12
Classifier: Programming Language :: Python :: 3 :: Only
Classifier: Topic :: Software Development :: Quality Assurance
Classifier: Topic :: Software Development :: Testing
Classifier: Topic :: Software Development :: Libraries
Requires-Dist: tomli>=2.2.1
Requires-Dist: typer>=0.12.5
License-File: LICENSE
Summary: An extremely fast Python library to calculate the cognitive complexity of Python files, written in Rust.
Keywords: cognitive,complexity,cognitive complexity,quality,quality assurance,testing,libraries,performance,sonar
Home-Page: https://github.com/rohaquinlop/complexipy
Author-email: Robin Quintero <rohaquinlop301@gmail.com>
License: MIT
Requires-Python: >=3.8
Project-URL: Homepage, https://github.com/rohaquinlop/complexipy
Project-URL: Documentation, https://rohaquinlop.github.io/complexipy/
Project-URL: Repository, https://github.com/rohaquinlop/complexipy
